README.md
setup.py
pie/__init__.py
pie/__main__.py
pie/config.py
pie/exceptions.py
pie/hooks.py
pie/ignore.py
pie/pie.py
pie_cli.egg-info/PKG-INFO
pie_cli.egg-info/SOURCES.txt
pie_cli.egg-info/dependency_links.txt
pie_cli.egg-info/entry_points.txt
pie_cli.egg-info/requires.txt
pie_cli.egg-info/top_level.txt