Metadata-Version: 2.1
Name: pie-cli
Version: 1.3.2
Summary: Pie, a complete version control.
Home-page: https://github.com/jaedsonpys/pie
Author: Jaedson Silva
Author-email: imunknowuser@protonmail.com
License: GPL v3.0
Keywords: version,control,versioning,file
Platform: UNKNOWN
Classifier: License :: OSI Approved :: GNU General Public License v3 (GPLv3)
Classifier: Development Status :: 5 - Production/Stable
Classifier: Intended Audience :: Developers
Classifier: Natural Language :: English
Classifier: Operating System :: Unix
Classifier: Programming Language :: Python :: 3
Classifier: Topic :: Software Development
Classifier: Topic :: Software Development :: Version Control
Requires-Python: >=3.7
